pypp
