Metadata-Version: 1.0
Name: pypp
Version: 0.0.3
Summary:  pypp: python preprocessor based on the Mako template engine
